samplerate.cpython-312-darwin.so
samplerate_ledfx-0.2.3.dist-info/RECORD
samplerate_ledfx-0.2.3.dist-info/WHEEL
samplerate_ledfx-0.2.3.dist-info/top_level.txt
samplerate_ledfx-0.2.3.dist-info/METADATA
samplerate_ledfx-0.2.3.dist-info/licenses/LICENSE.rst
