Metadata-Version: 2.4
Name: samplerate-ledfx
Version: 0.2.3
Summary: Monolithic python wrapper for libsamplerate based on pybind11 and NumPy
Author-email: Robin Scheibler <fakufaku@gmail.com>, Tino Wagner <ich@tinowagner.com>
Keywords: samplerate,converter,signal processing,audio
Classifier: Development Status :: 3 - Alpha
Classifier: Environment :: Console
Classifier: Intended Audience :: Developers
Classifier: Intended Audience :: Science/Research
Classifier: Operating System :: OS Independent
Classifier: Programming Language :: Python :: 3
Classifier: Topic :: Scientific/Engineering
Classifier: Topic :: Multimedia :: Sound/Audio
Requires-Python: >=3.9
License-File: LICENSE.rst
Requires-Dist: numpy>=1.7.0
Dynamic: license-file
